aio_pika_rpc/__init__.py
aio_pika_rpc/msgpack_rpc.py
aio_pika_rpc-1.2.0.dist-info/LICENSE
aio_pika_rpc-1.2.0.dist-info/WHEEL
aio_pika_rpc-1.2.0.dist-info/METADATA
aio_pika_rpc-1.2.0.dist-info/RECORD
